MANIFEST.in
README.md
setup.cfg
setup.py
versioneer.py
src/kabaret/__init__.py
src/kabaret.sqarf_flow.egg-info/PKG-INFO
src/kabaret.sqarf_flow.egg-info/SOURCES.txt
src/kabaret.sqarf_flow.egg-info/dependency_links.txt
src/kabaret.sqarf_flow.egg-info/requires.txt
src/kabaret.sqarf_flow.egg-info/top_level.txt
src/kabaret/sqarf_flow/__init__.py
src/kabaret/sqarf_flow/_version.py
src/kabaret/sqarf_flow/export.py
src/kabaret/sqarf_flow/extra_tests.py
src/kabaret/sqarf_flow/qagroup.py
src/kabaret/sqarf_flow/qareport.py
src/kabaret/sqarf_flow/resources/__init__.py
src/kabaret/sqarf_flow/resources/icons/__init__.py
src/kabaret/sqarf_flow/resources/icons/sqarf.png
src/kabaret/sqarf_flow/resources/icons/sqarf_icon.png