Metadata-Version: 2.1
Name: kabaret.sqarf-flow
Version: 1.0.0
Summary: Kabaret flow extension to quality test your assets using https://pypi.org/project/sqarf
Home-page: https://gitlab.com/kabaretstudio/kabaret.sqarf_flow
Author: Damien "dee" Coureau
Author-email: kabaret-dev@googlegroups.com
License: LGPLv3+
Keywords: kabaret blender b3d pipeline dataflow workflow
Platform: UNKNOWN
Classifier: Development Status :: 3 - Alpha
Classifier: Intended Audience :: Developers
Classifier: Operating System :: OS Independent
Classifier: Programming Language :: Python :: 3.7
Classifier: License :: OSI Approved :: GNU Lesser General Public License v3 or later (LGPLv3+)
